versions/__init__.py
versions/__main__.py
versions/constants.py
versions/converters.py
versions/converters_utils.py
versions/errors.py
versions/functions.py
versions/main.py
versions/meta.py
versions/operators.py
versions/parsers.py
versions/patterns.py
versions/phases.py
versions/py.typed
versions/representation.py
versions/segments/__init__.py
versions/segments/constants.py
versions/segments/epoch.py
versions/segments/local.py
versions/segments/release.py
versions/segments/tags.py
versions/segments/typing.py
versions/specification.py
versions/specifiers.py
versions/string.py
versions/types.py
versions/utils.py
versions/version.py
versions/version_sets.py
versions/versioned.py
versions-2.1.1.dist-info/LICENSE
versions-2.1.1.dist-info/METADATA
versions-2.1.1.dist-info/WHEEL
versions-2.1.1.dist-info/RECORD
