Metadata-Version: 2.1
Name: versions
Version: 2.1.1
Summary: Parsing, inspecting and specifying versions.
Home-page: https://github.com/nekitdev/versions
License: MIT
Keywords: python,semver,version
Author: nekitdev
Requires-Python: >=3.8
Classifier: Development Status :: 5 - Production/Stable
Classifier: Intended Audience :: Developers
Classifier: License :: OSI Approved :: MIT License
Classifier: Operating System :: OS Independent
Classifier: Programming Language :: Python :: 3
Classifier: Programming Language :: Python :: 3.8
Classifier: Programming Language :: Python :: 3.9
Classifier: Programming Language :: Python :: 3.10
Classifier: Programming Language :: Python :: 3.11
Classifier: Programming Language :: Python :: 3.12
Classifier: Topic :: Utilities
Classifier: Typing :: Typed
Requires-Dist: attrs (>=23.2.0,<24.0.0)
Requires-Dist: click (>=8.1.7,<9.0.0)
Requires-Dist: entrypoint (>=2.0.1,<3.0.0)
Requires-Dist: funcs (>=0.9.0,<0.10.0)
Requires-Dist: iters (>=0.15.0,<0.16.0)
Requires-Dist: orderings (>=1.3.0,<2.0.0)
Requires-Dist: solus (>=1.1.0,<2.0.0)
Requires-Dist: typing-aliases (>=1.7.0,<2.0.0)
Requires-Dist: typing-extensions (>=4.9.0,<5.0.0)
Project-URL: Chat, https://nekit.dev/chat
Project-URL: Documentation, https://nekitdev.github.io/versions
Project-URL: Funding, https://nekit.dev/funding
Project-URL: Issues, https://github.com/nekitdev/versions/issues
Project-URL: Repository, https://github.com/nekitdev/versions
